cli_logging_moxad/__init__.py
cli_logging_moxad/logging_utils.py
cli_logging_moxad-0.7.0.dist-info/METADATA
cli_logging_moxad-0.7.0.dist-info/WHEEL
cli_logging_moxad-0.7.0.dist-info/licenses/LICENSE.txt
cli_logging_moxad-0.7.0.dist-info/RECORD
