Metadata-Version: 2.4
Name: cli_logging_moxad
Version: 0.7.0
Summary: colored logging to terminal for CLI scripts
Project-URL: Homepage, https://github.com/rjwhite/cli-logging
Author-email: RJ White <rj.white@moxad.com>
License-File: LICENSE.txt
Classifier: Intended Audience :: Developers
Classifier: License :: OSI Approved :: GNU General Public License v3 (GPLv3)
Classifier: Natural Language :: English
Classifier: Operating System :: POSIX :: Linux
Classifier: Programming Language :: Python
Classifier: Programming Language :: Python :: 3
Requires-Dist: colorlog>=6.9.0
